{
"type": "FeatureCollection",
"crs": { "type": "name", "properties": { "name": "urn:ogc:def:crs:OGC:1.3:CRS84" } },
                                                                                
"features": [
{ "type": "Feature", "properties": { "OBJECTID": 608, "ADDRESS_ID": 117007, "FISCAL_YEAR": 2013, "APPLICANT": "Joy Jones", "INDIVIDUAL": "Joy Jones", "ORGANIZATION": null, "ADDRESS": "1031 MICHIGAN AVENUE NE", "ADDRESS2": "#205", "CITY": "WASHINGTON", "STATE": "DC", "ZIP_4": "20017", "GRANT_CATEGORY": "Arts and Healing Grant (Individual)", "DISCIPLINE": "Literature", "GRANT_": 6267, "URL": null, "WARD": 5, "X_COORD": 400677.25, "Y_COORD": 140898.52 }, "geometry": { "type": "Point", "coordinates": [ -76.992190869799998, 38.9359797603 ] } },
{ "type": "Feature", "properties": { "OBJECTID": 689, "ADDRESS_ID": 235733, "FISCAL_YEAR": 2013, "APPLICANT": "Ruth Stenstrom", "INDIVIDUAL": "Ruth Stenstrom", "ORGANIZATION": null, "ADDRESS": "1736 COLUMBIA ROAD NW", "ADDRESS2": "#303", "CITY": "WASHINGTON", "STATE": "DC", "ZIP_4": "20009-2847", "GRANT_CATEGORY": "Arts and Healing Grant (Individual)", "DISCIPLINE": "Visual Arts", "GRANT_": 10000, "URL": null, "WARD": 1, "X_COORD": 396530.88, "Y_COORD": 139590.89 }, "geometry": { "type": "Point", "coordinates": [ -77.040008541399999, 38.924193634799998 ] } },
{ "type": "Feature", "properties": { "OBJECTID": 703, "ADDRESS_ID": 72007, "FISCAL_YEAR": 2013, "APPLICANT": "Margot Greenlee", "INDIVIDUAL": "Margot Greenlee", "ORGANIZATION": null, "ADDRESS": "1205 G STREET NE", "ADDRESS2": null, "CITY": "WASHINGTON", "STATE": "DC", "ZIP_4": "20002", "GRANT_CATEGORY": "Arts and Healing Grant (Individual)", "DISCIPLINE": "Dance", "GRANT_": 9850, "URL": null, "WARD": 6, "X_COORD": 400878.26, "Y_COORD": 136761.91 }, "geometry": { "type": "Point", "coordinates": [ -76.989877707299996, 38.898715627500003 ] } },
{ "type": "Feature", "properties": { "OBJECTID": 807, "ADDRESS_ID": 81705, "FISCAL_YEAR": 2013, "APPLICANT": "Andrene Taylor", "INDIVIDUAL": "Andrene Taylor", "ORGANIZATION": null, "ADDRESS": "901 JACKSON STREET NE", "ADDRESS2": null, "CITY": "WASHINGTON", "STATE": "DC", "ZIP_4": "20017", "GRANT_CATEGORY": "Arts and Healing Grant (Individual)", "DISCIPLINE": "Visual Arts", "GRANT_": 10000, "URL": null, "WARD": 5, "X_COORD": 400561.01, "Y_COORD": 140152.76 }, "geometry": { "type": "Point", "coordinates": [ -76.993532192700002, 38.929261807700001 ] } }
]
}
