{"type":"FeatureCollection","features":[{"type":"Feature","properties":{"OBJECTID":906,"FISCAL_YEAR":2015,"APPLICANT":"Mazi Mutafa","ORGANIZATION":"Words, Beats, & Life, Inc.","ADDRESS":"1525 NEWTON STREET NW","ADDRESS2":null,"ZIP_4":"20010","GRANT_CATEGORY":"Upstart","DISCIPLINE":"Multi-Disciplinary","GRANT_":75000,"URL":"http://wblinc.org","WARD":1},"geometry":{"type":"Point","coordinates":[-77.03575012673143,38.93348727045944]}},{"type":"Feature","properties":{"OBJECTID":907,"FISCAL_YEAR":2015,"APPLICANT":"Amy Saidman","ORGANIZATION":"Washington Storytellers Theatre","ADDRESS":"1525 NEWTON STREET NW","ADDRESS2":null,"ZIP_4":"20010","GRANT_CATEGORY":"Upstart","DISCIPLINE":"Oral Traditions","GRANT_":75000,"URL":"http://speakeasydc.org","WARD":1},"geometry":{"type":"Point","coordinates":[-77.03575012673143,38.93348727045944]}},{"type":"Feature","properties":{"OBJECTID":925,"FISCAL_YEAR":2015,"APPLICANT":"Allison Stockman","ORGANIZATION":"Constellation Theatre Company","ADDRESS":"1835 14TH STREET NW","ADDRESS2":null,"ZIP_4":"20009","GRANT_CATEGORY":"Upstart","DISCIPLINE":"Theatre","GRANT_":75000,"URL":"http://constellationtheatre.org/index.html","WARD":1},"geometry":{"type":"Point","coordinates":[-77.03158602013413,38.91521067743368]}},{"type":"Feature","properties":{"OBJECTID":926,"FISCAL_YEAR":2015,"APPLICANT":"Mark Chalfant","ORGANIZATION":"Washington Improvisational Theater Co","ADDRESS":"1835 14TH STREET NW","ADDRESS2":null,"ZIP_4":"20009-4425","GRANT_CATEGORY":"Upstart","DISCIPLINE":"Theatre","GRANT_":75000,"URL":"http://washingtonimprovtheater.com","WARD":1},"geometry":{"type":"Point","coordinates":[-77.03158602013413,38.91521067743368]}},{"type":"Feature","properties":{"OBJECTID":984,"FISCAL_YEAR":2015,"APPLICANT":"Callahan","ORGANIZATION":"826DC","ADDRESS":"3233 14TH STREET NW","ADDRESS2":null,"ZIP_4":"20010","GRANT_CATEGORY":"Upstart","DISCIPLINE":"Literature","GRANT_":75000,"URL":"http://826dc.org","WARD":1},"geometry":{"type":"Point","coordinates":[-77.0321466908113,38.930171187871615]}},{"type":"Feature","properties":{"OBJECTID":1020,"FISCAL_YEAR":2015,"APPLICANT":"Caitlin Wood","ORGANIZATION":"CAPITAL FRINGE INC","ADDRESS":"607 NEW YORK AVENUE NW","ADDRESS2":null,"ZIP_4":"20001","GRANT_CATEGORY":"Upstart","DISCIPLINE":"Multi-Disciplinary","GRANT_":75000,"URL":"http://capitalfringe.org","WARD":6},"geometry":{"type":"Point","coordinates":[-77.02034555868845,38.90377627064401]}}]}